asymmetree/__init__.py
asymmetree/analysis/BestMatches.py
asymmetree/analysis/HGT.py
asymmetree/analysis/__init__.py
asymmetree/file_io/SeqFileIO.py
asymmetree/file_io/SubstModelIO.py
asymmetree/file_io/__init__.py
asymmetree/genome/GenomeSimulation.py
asymmetree/genome/__init__.py
asymmetree/seqevolve/Alignment.py
asymmetree/seqevolve/EmpiricalModels.py
asymmetree/seqevolve/Evolver.py
asymmetree/seqevolve/EvolvingSequence.py
asymmetree/seqevolve/HetModel.py
asymmetree/seqevolve/IndelModel.py
asymmetree/seqevolve/SubstModel.py
asymmetree/seqevolve/__init__.py
asymmetree/tools/DistanceCalculation.py
asymmetree/tools/PhyloTreeTools.py
asymmetree/tools/Sampling.py
asymmetree/tools/__init__.py
asymmetree/treeevolve/DistanceNoise.py
asymmetree/treeevolve/GeneTree.py
asymmetree/treeevolve/RateHeterogeneity.py
asymmetree/treeevolve/SpeciesTree.py
asymmetree/treeevolve/__init__.py
asymmetree/visualize/TreeVis.py
asymmetree/visualize/__init__.py
asymmetree-2.2.1.dist-info/LICENSE
asymmetree-2.2.1.dist-info/METADATA
asymmetree-2.2.1.dist-info/WHEEL
asymmetree-2.2.1.dist-info/top_level.txt
asymmetree-2.2.1.dist-info/RECORD
