Metadata-Version: 2.1
Name: asymmetree
Version: 2.2.1
Summary: Simulation of phylogenetic trees, sequences and genomes
Home-page: https://github.com/david-schaller/AsymmeTree
Author: David Schaller
Author-email: sdavid@bioinf.uni-leipzig.de
Project-URL: Bug Tracker, https://github.com/david-schaller/AsymmeTree/issues
Classifier: Programming Language :: Python :: 3
Classifier: License :: OSI Approved :: GNU General Public License v3 (GPLv3)
Classifier: Operating System :: OS Independent
Requires-Python: >=3.7
License-File: LICENSE
Requires-Dist: numpy
Requires-Dist: scipy
Requires-Dist: matplotlib
Requires-Dist: networkx
Requires-Dist: tralda
